src/OpenCC_gui.py
src/__init__.py
src/assets/favicon.ico
src/assets/right_arrow.png
OpenCC_GUI-1.1.5.post1.dist-info/LICENSE
OpenCC_GUI-1.1.5.post1.dist-info/METADATA
OpenCC_GUI-1.1.5.post1.dist-info/WHEEL
OpenCC_GUI-1.1.5.post1.dist-info/entry_points.txt
OpenCC_GUI-1.1.5.post1.dist-info/top_level.txt
OpenCC_GUI-1.1.5.post1.dist-info/RECORD
