Metadata-Version: 2.1
Name: OpenCC-GUI
Version: 1.1.5.post1
Summary: A simple GUI for OpenCC
Home-page: https://github.com/ilvon/OpenCC-GUI
Author: iivon
Classifier: Programming Language :: Python :: 3
Classifier: Operating System :: Microsoft :: Windows
Classifier: Operating System :: Unix
Classifier: Operating System :: MacOS :: MacOS X
Requires-Python: >=3.10
License-File: LICENSE
Requires-Dist: chardet>=5.2.0
Requires-Dist: CTkMessagebox>=2.7
Requires-Dist: customtkinter>=5.2.2
Requires-Dist: OpenCC>=1.1.9
